reina/__init__.py
reina/MetaLearners/SLearner.py
reina/MetaLearners/TLearner.py
reina/MetaLearners/XLearner.py
reina/MetaLearners/__init__.py
reina/Utilities/__init__.py
reina/Utilities/baseModel.py
reina/iv/__init__.py
reina/iv/tsls.py
reina-0.0.6.dist-info/LICENSE.txt
reina-0.0.6.dist-info/METADATA
reina-0.0.6.dist-info/WHEEL
reina-0.0.6.dist-info/top_level.txt
reina-0.0.6.dist-info/RECORD
