Metadata-Version: 2.1
Name: reina
Version: 0.0.6
Summary: A Causal Inference library for Big Data.
Home-page: https://github.com/Qyu-ai/Reina/
Author: Qyu.ai Inc.
Author-email: soumil@qyu.ai
License: UNKNOWN
Project-URL: Bug Tracker, https://github.com/Qyu-ai/Reina/issues
Platform: UNKNOWN
Classifier: Programming Language :: Python :: 3
Classifier: License :: OSI Approved :: MIT License
Classifier: Operating System :: OS Independent
Requires-Python: >=3.6
License-File: LICENSE.txt
Requires-Dist: py4j (>=0.10.9)
Requires-Dist: numpy (>=1.7)
Requires-Dist: pandas (>=0.23.2)
Requires-Dist: pyarrow (>=1.0.0)
Requires-Dist: pyspark
